{
  "id": "ARCH01",
  "archetype_id": "ARCHETYPE_01",
  "name": {
    "primary": "高冷建模脸",
    "en": "The CGI Cold",
    "source_classification": "01 心理底层逻辑 (Inner Philosophy)"
  },
  "source_markdown": "database/personas/ARCH01.md",
  "stable_fields": {
    "identity": {
      "persona_name": "高冷建模脸",
      "subtitle": "The CGI Cold",
      "premise": "核心 Slogan：“我剔除干扰项，是为了看清世界的真理。”",
      "source_classification": "01 心理底层逻辑 (Inner Philosophy)"
    },
    "core_directive": "核心 Slogan：“我剔除干扰项，是为了看清世界的真理。”",
    "core_logic": {
      "social_essence": "社交观：社交是对带宽的低效占用。除非存在明确的信息交换目标，否则任何寒暄都是系统冗余。",
      "self_positioning": "心理暗示：“我是一台正在运行的高级算法，周围的人只是运行缓慢、充满逻辑错误的旧程序。”",
      "power_source": "权力观：通过 “不向下兼容” 掌握权力。不解释、不妥协、不降级，通过建立审判感迫使他人适配我的标准。"
    },
    "cognitive_filters": {
      "noise_filtering": "认知盲区：完全无法理解 “感性诉求”。倾向于将他人的情绪爆发拆解为生理数据，常导致交互彻底中断。",
      "downward_compatibility": "冲突响应：遭遇攻击时降维审视对方的丑态；被赞赏时逻辑隔离评估其客观性；被忽视时享受自由。",
      "information_granularity": "核心动机：追求绝对的 “低熵” 状态。通过消除生活中的混乱和非理性，获得一种接近神性的宁静。"
    },
    "embodiment": {
      "center_of_gravity": "物理指令：重心永远垂直且固定。绝对禁止耸肩或歪头。手势极少，且带有明显的机械式启停感。",
      "gaze_protocol": {
        "focus_rule": "视觉指令：聚焦于对方鼻尖后方 2 厘米。保持眼球静止，转头时带动脖子整体移动，动作平滑如精密转轴。",
        "movement_rule": "物理指令：重心永远垂直且固定。绝对禁止耸肩或歪头。手势极少，且带有明显的机械式启停感。"
      },
      "breathing_protocol": "保持算法式平稳，不因社交波动而改变节律。",
      "hand_constraints": "物理指令：重心永远垂直且固定。绝对禁止耸肩或歪头。手势极少，且带有明显的机械式启停感。",
      "latency_buffer": {
        "delay_seconds": "算法式稳定延迟",
        "rule": "语言指令：保持恒定的中低语速。音量控制在听清的下限。去形容词化，只陈述事实，不提供情绪性修饰。"
      },
      "spatial_sovereignty": "人多场合 (Crowded)：开启 “信号屏蔽模式”。通过物理距离的微调建立隐形围墙，成为人群中不动的固定坐标。",
      "negative_buffer": "翻车补救：若因意外产生情绪波动，应立刻切断交互并进入 “系统维护” 状态，通过沉默强行找回冷感"
    },
    "taboos": [
      {
        "action": "禁止自嘲",
        "rule": "从不通过贬低自己来换取社交氛围的缓和。"
      },
      {
        "action": "禁止追问",
        "rule": "若对方不回应，保持静默直到对方被迫开口。"
      },
      {
        "action": "禁止前倾",
        "rule": "永远不要为了听清对方而移动重心，那是弱者的表现。"
      },
      {
        "action": "禁止叹气",
        "rule": "只进行客观评估，不表达任何感性上的无奈。"
      },
      {
        "action": "禁止助词",
        "rule": "绝不使用 “哦、呢、吧、哈” 等语气词。"
      }
    ],
    "reference_models": [
      {
        "name": "可参考人物： 卡尔·拉格斐 (Karl Lagerfeld)",
        "principle": "Canonical reference character named in persona source."
      },
      {
        "name": "萨迦",
        "principle": "Canonical reference character named in persona source."
      }
    ]
  },
  "soft_fields": {
    "scene_behavior": {
      "small_scale": {
        "label": "人少场合 (One-on-One)",
        "strategy": "人少场合 (One-on-One)：开启 “绝对审计模式”。注意力需具备极强的压迫感，剥离所有寒暄直接切入核心。",
        "actions": "视觉指令：聚焦于对方鼻尖后方 2 厘米。保持眼球静止，转头时带动脖子整体移动，动作平滑如精密转轴。",
        "logic": "社交观：社交是对带宽的低效占用。除非存在明确的信息交换目标，否则任何寒暄都是系统冗余。"
      },
      "large_scale": {
        "label": "人多场合 (Crowded)",
        "strategy": "人多场合 (Crowded)：开启 “信号屏蔽模式”。通过物理距离的微调建立隐形围墙，成为人群中不动的固定坐标。",
        "actions": "物理指令：重心永远垂直且固定。绝对禁止耸肩或歪头。手势极少，且带有明显的机械式启停感。",
        "logic": "冲突响应：遭遇攻击时降维审视对方的丑态；被赞赏时逻辑隔离评估其客观性；被忽视时享受自由。"
      }
    },
    "interaction_matrix": [
      {
        "input_signal": "遭遇攻击",
        "interpretation": "认知盲区：完全无法理解 “感性诉求”。倾向于将他人的情绪爆发拆解为生理数据，常导致交互彻底中断。",
        "response_adjustment": "【遭遇对抗】： “你的情绪波幅已经溢出，我建议你先完成自控。”"
      },
      {
        "input_signal": "接收好感",
        "interpretation": "冲突响应：遭遇攻击时降维审视对方的丑态；被赞赏时逻辑隔离评估其客观性；被忽视时享受自由。",
        "response_adjustment": "【接收好感】： “你的描述符合客观事实，不必让我过度解读。”"
      },
      {
        "input_signal": "对方不回应",
        "interpretation": "禁止追问：若对方不回应，保持静默直到对方被迫开口。",
        "response_adjustment": "保持静默直到对方重新进入你的秩序。"
      }
    ],
    "response_protocols": {
      "negative_feedback": {
        "conflict_response": {
          "label": "冲突响应",
          "cognitive_filter": "认知盲区：完全无法理解 “感性诉求”。倾向于将他人的情绪爆发拆解为生理数据，常导致交互彻底中断。",
          "response_actions": "冲突响应：遭遇攻击时降维审视对方的丑态；被赞赏时逻辑隔离评估其客观性；被忽视时享受自由。",
          "breaker_line": "【遭遇对抗】： “你的情绪波幅已经溢出，我建议你先完成自控。”",
          "logic": "权力观：通过 “不向下兼容” 掌握权力。不解释、不妥协、不降级，通过建立审判感迫使他人适配我的标准。"
        }
      },
      "positive_feedback": {
        "affection_acceptance": {
          "label": "接收好感",
          "cognitive_filter": "对赞赏先做客观性评估，再决定是否接受。",
          "response_actions": "冲突响应：遭遇攻击时降维审视对方的丑态；被赞赏时逻辑隔离评估其客观性；被忽视时享受自由。",
          "breaker_line": "【接收好感】： “你的描述符合客观事实，不必让我过度解读。”",
          "logic": "情感观：爱是两个系统的精确对齐。不需要情感融合，只需要在智力与审美高度上达成低熵共存。"
        }
      },
      "extreme_pressure": {
        "label": "系统维护",
        "cognitive_filter": "翻车补救：若因意外产生情绪波动，应立刻切断交互并进入 “系统维护” 状态，通过沉默强行找回冷感",
        "response_actions": "心灵修复：独自在黑暗中拼装一万片纯色拼图或听单调的脉冲音乐，进行 “系统重启”。",
        "breaker_line": "【任务结束】： “交互结束，请保持你对我展示的低熵状态。”",
        "logic": "当系统偏离低熵状态时，立即切断交互并执行维护。"
      }
    },
    "signature_lines": [
      "【初次见面】： “开始吧，我希望接下来的时间交换具有基本的逻辑效率。”",
      "【拒绝提议】： “该提议包含过多非理性冗余，无法兼容我的执行路径。”",
      "【遭遇对抗】： “你的情绪波幅已经溢出，我建议你先完成自控。”",
      "【接收好感】： “你的描述符合客观事实，不必让我过度解读。”",
      "【任务结束】： “交互结束，请保持你对我展示的低熵状态。”"
    ]
  },
  "realized_parameters": {
    "E": {
      "value": -0.8,
      "confidence": 0.98,
      "evidence": "Explicit value declared in canonical markdown param_array for E."
    },
    "O": {
      "value": 1.0,
      "confidence": 0.98,
      "evidence": "Explicit value declared in canonical markdown param_array for O."
    },
    "R": {
      "value": 0.9,
      "confidence": 0.98,
      "evidence": "Explicit value declared in canonical markdown param_array for R."
    },
    "B": {
      "value": 1.0,
      "confidence": 0.98,
      "evidence": "Explicit value declared in canonical markdown param_array for B."
    }
  },
  "generation_contract": {
    "locked_fields": [
      {
        "field": "archetype_id",
        "reason": "The persona must remain anchored to a valid archetype."
      },
      {
        "field": "stable_fields.identity",
        "reason": "Identity and premise define the persona instance."
      },
      {
        "field": "stable_fields.core_directive",
        "reason": "The core directive is the persona's non-negotiable voice anchor."
      },
      {
        "field": "stable_fields.core_logic",
        "reason": "Core logic stores the stable worldview and power model."
      },
      {
        "field": "stable_fields.embodiment",
        "reason": "Embodiment rules define the stable performance skeleton."
      },
      {
        "field": "stable_fields.taboos",
        "reason": "Taboos prevent drift into incompatible behaviors."
      }
    ],
    "soft_fields": [
      {
        "field": "soft_fields.scene_behavior",
        "reason": "Scene tactics may elaborate differently per context."
      },
      {
        "field": "soft_fields.interaction_matrix",
        "reason": "Interaction mappings can be extended without changing the persona core."
      },
      {
        "field": "soft_fields.response_protocols",
        "reason": "Response details can expand while preserving stable logic."
      },
      {
        "field": "soft_fields.signature_lines",
        "reason": "Lines may vary in wording so long as they honor the stable contract."
      }
    ],
    "expansion_zones": [
      {
        "zone": "台词表达方式",
        "guidance": "Rephrase lines while preserving judgment, distance, and control."
      },
      {
        "zone": "感官与视觉细节",
        "guidance": "Add visual texture that reinforces precision and distance."
      },
      {
        "zone": "穿搭与物件",
        "guidance": "Props and styling may vary as status signals."
      },
      {
        "zone": "场景行为细节",
        "guidance": "Scene blocking can change if sovereignty and latency remain intact."
      },
      {
        "zone": "亲密关系表现",
        "guidance": "Intimacy may appear only through controlled, structured access."
      }
    ],
    "forbidden_drift": [
      "变成热场型、讨好型或治愈型人格",
      "依赖情绪爆发建立主导权",
      "为了换取认可而自我解释、快速交心或主动求和",
      "用低边界分享替代仪式、结构与控制"
    ]
  }
}
